pdftitle/__init__.py
pdftitle/constants.py
pdftitle/device.py
pdftitle/exceptions.py
pdftitle/interpreter.py
pdftitle/metadata.py
pdftitle/openai_gateway.py
pdftitle/pdftitle.py
pdftitle-0.20.dist-info/LICENSE
pdftitle-0.20.dist-info/METADATA
pdftitle-0.20.dist-info/WHEEL
pdftitle-0.20.dist-info/entry_points.txt
pdftitle-0.20.dist-info/top_level.txt
pdftitle-0.20.dist-info/RECORD
