Metadata-Version: 2.2
Name: pdftitle
Version: 0.20
Summary: pdftitle is a small utility to extract the title from a PDF file
Author-email: Mete Balci <metebalci@gmail.com>
Project-URL: Homepage, https://github.com/metebalci/pdftitle
Project-URL: Documentation, https://github.com/metebalci/pdftitle
Project-URL: Repository, https://github.com/metebalci/pdftitle.git
Project-URL: Issues, https://github.com/metebalci/pdftitle/issues
Project-URL: Changelog, https://github.com/metebalci/pdftitle/blob/master/CHANGELOG.md
Keywords: pdf,title,text,extract
Classifier: Development Status :: 3 - Alpha
Classifier: Environment :: Console
Classifier: Intended Audience :: Science/Research
Classifier: License :: OSI Approved :: GNU General Public License v3 (GPLv3)
Classifier: Topic :: Utilities
Classifier: Programming Language :: Python :: 3.8
Requires-Python: >=3.8
License-File: LICENSE
Requires-Dist: pdfminer.six>=20240706
Requires-Dist: python-dotenv
Provides-Extra: dev
Requires-Dist: openai; extra == "dev"
Requires-Dist: setuptools>=61.0; extra == "dev"
Requires-Dist: black; extra == "dev"
Requires-Dist: pylint; extra == "dev"
Requires-Dist: build; extra == "dev"
Requires-Dist: twine; extra == "dev"
Requires-Dist: reuse; extra == "dev"
